Metadata-Version: 2.1
Name: unicode-text-styler
Version: 1.0.0
Summary: Convert ASCII alphanumeric text to a random style using Unicode character normalization.
Home-page: https://github.com/ssrathi/text_styler
Author: Shyamsunder Rathi
Author-email: shyam29@gmail.com
License: MIT
Download-URL: https://github.com/ssrathi/text_styler/archive/1.0.0.tar.gz
Keywords: unicode,text,styler,normalization
Platform: UNKNOWN
Classifier: Development Status :: 5 - Production/Stable
Classifier: Programming Language :: Python :: 3
Classifier: Topic :: Software Development
Classifier: Operating System :: OS Independent
Classifier: License :: OSI Approved :: MIT License
Requires-Python: >=3
